Metadata-Version: 2.1
Name: saltible
Version: 0.0.1
Summary: An util help to easily use salt-ssh without root
Home-page: https://github.com/hvnsweeting/saltible
Author: Viet Hung Nguyen
Author-email: hvn@familug.org
License: UNKNOWN
Project-URL: Bug Tracker, https://github.com/hvnsweeting/saltible/issues
Platform: UNKNOWN
Classifier: Programming Language :: Python :: 3
Classifier: License :: OSI Approved :: MIT License
Classifier: Operating System :: OS Independent
Requires-Python: >=3.6
